AUTHORS.rst
CONTRIBUTING.rst
HISTORY.rst
LICENSE
MANIFEST.in
README.rst
setup.cfg
setup.py
docs/Makefile
docs/authors.rst
docs/conf.py
docs/contributing.rst
docs/history.rst
docs/index.rst
docs/installation.rst
docs/make.bat
docs/readme.rst
docs/usage.rst
nstv/__init__.py
nstv/nstv.py
nstv.egg-info/PKG-INFO
nstv.egg-info/SOURCES.txt
nstv.egg-info/dependency_links.txt
nstv.egg-info/not-zip-safe
nstv.egg-info/top_level.txt
tests/__init__.py
tests/test_nstv.py