Metadata-Version: 1.2
Name: nstv
Version: 0.0.1
Summary:  
Home-page: https://github.com/kcinnick/nstv
Author: Nick Tucker
Author-email: nicktucker4@gmail.com
License: MIT license
Keywords: nstv
Platform: UNKNOWN
Classifier: Development Status :: 2 - Pre-Alpha
Classifier: Intended Audience :: Developers
Classifier: License :: OSI Approved :: MIT License
Classifier: Natural Language :: English
Classifier: Programming Language :: Python :: 3
Classifier: Programming Language :: Python :: 3.5
Classifier: Programming Language :: Python :: 3.6
Classifier: Programming Language :: Python :: 3.7
Classifier: Programming Language :: Python :: 3.8
Requires-Python: >=3.5
